easy_leasy/__init__.py
easy_leasy/_base.py
easy_leasy/_operations.py
easy_leasy/_parser.py
easy_leasy/_scalars.py
easy_leasy/py.typed
easy_leasy-1.0.1.dist-info/METADATA
easy_leasy-1.0.1.dist-info/WHEEL
easy_leasy-1.0.1.dist-info/RECORD
