Metadata-Version: 2.1
Name: easy-leasy
Version: 1.0.1
Summary: Easy Leasy is a time set manipulation library
License: WTFPL
Author: Rémy Sanchez
Author-email: remy.sanchez@hyperthese.net
Requires-Python: >=3.10,<4.0
Classifier: License :: Other/Proprietary License
Classifier: Programming Language :: Python :: 3
Classifier: Programming Language :: Python :: 3.10
Classifier: Programming Language :: Python :: 3.11
Classifier: Programming Language :: Python :: 3.12
Requires-Dist: lark
Requires-Dist: python-dateutil
